{
    "name" : "Template",
    "state" : "lobby",
    "host" : "",
    "code" : "",
    "word" : "",
    "prevWord": "",
    "turn" : -1,
    "time" : {
        "drawLimit" : 120,
        "bufferLimit" : 5,
        "timeRemain" : 0,
        "active" : 0,
        "buffer": 0,
        "idle" : 0,
        "idleSum" : 0
    },
    "teams" : {
        "team1": {
            "players" :  [],
            "drawIndex" : 0,
            "points" : 0,
            "isActive" : false,
            "isWinner" : false
        },
        "team2": {
            "players" :  [],
            "drawIndex" : 0,
            "points" : 0,
            "isActive" : false,
            "isWinner" : false
        },
        "team3": {
            "players" :  [],
            "drawIndex" : 0,
            "points" : 0,
            "isActive" : false,
            "isWinner" : false
        },
        "team4": {
            "players" :  [],
            "drawIndex" : 0,
            "points" : 0,
            "isActive" : false,
            "isWinner" : false
        }     
    }
}